{"version":"1.6","studentIndex":0,"active":true,"name":"Marco","totalStars":0,"mapLimit":2,"goldCoins":995,"masterVol":0.5239999890327454,"musicVol":0.20399999618530274,"fxVol":0.6069999933242798,"talkVol":0.6499999761581421,"micDevice":0,"stickerTutorial":true,"froggerTutorial":true,"turntablesTutorial":true,"spiderwebTutorial":true,"rummageTutorial":true,"currStoryBeat":6,"unlockedStickerButton":true,"mapData":{"GV_house1":{"isFixed":true,"stars":2},"GV_house2":{"isFixed":true,"stars":3},"GV_fire":{"isFixed":true,"stars":3},"GV_statue":{"isFixed":true,"stars":3}},"unlockedStickers":[{"instanceID":0},{"instanceID":0},{"instanceID":0},{"instanceID":20762},{"instanceID":20764}]}